{
  "routeCode": "1",
  "routeName": "公交1路",
  "direction": "唐闸古镇公交停车场 -> 环西文化广场①",
  "startStation": "唐闸古镇公交停车场",
  "endStation": "环西文化广场①",
  "coordinateSystem": "tencent",
  "stations": [
    { "stationOrder": 1, "stationName": "唐闸古镇公交停车场", "longitude": 120.799369, "latitude": 32.061311 },
    { "stationOrder": 2, "stationName": "疏航桥", "longitude": 120.797155, "latitude": 32.064539 },
    { "stationOrder": 3, "stationName": "新华二村", "longitude": 120.795263, "latitude": 32.067427 },
    { "stationOrder": 4, "stationName": "新华佳园", "longitude": 120.792137, "latitude": 32.069832 },
    { "stationOrder": 5, "stationName": "大生桥", "longitude": 120.788215, "latitude": 32.071458 },
    { "stationOrder": 6, "stationName": "大生路黄海路北", "longitude": 120.785134, "latitude": 32.068376 },
    { "stationOrder": 7, "stationName": "黄海路大生路口", "longitude": 120.782069, "latitude": 32.065294 },
    { "stationOrder": 8, "stationName": "理工学院南", "longitude": 120.785627, "latitude": 32.061925 },
    { "stationOrder": 9, "stationName": "金融科技城・保险产业园", "longitude": 120.789158, "latitude": 32.058711 },
    { "stationOrder": 10, "stationName": "黄海路永和路西", "longitude": 120.792716, "latitude": 32.055342 },
    { "stationOrder": 11, "stationName": "盛和永兴花苑", "longitude": 120.796274, "latitude": 32.051973 },
    { "stationOrder": 12, "stationName": "黄海路永扬路口", "longitude": 120.799835, "latitude": 32.048615 },
    { "stationOrder": 13, "stationName": "黄海路江海大道西", "longitude": 120.803152, "latitude": 32.044927 },
    { "stationOrder": 14, "stationName": "五水商圈・宜家站", "longitude": 120.807269, "latitude": 32.041193 },
    { "stationOrder": 15, "stationName": "五水商圈・万达站", "longitude": 120.811357, "latitude": 32.037568 },
    { "stationOrder": 16, "stationName": "城闸大桥南", "longitude": 120.815974, "latitude": 32.033752 },
    { "stationOrder": 17, "stationName": "城港北村", "longitude": 120.821536, "latitude": 32.030227 },
    { "stationOrder": 18, "stationName": "节制闸新村", "longitude": 120.826183, "latitude": 32.027651 },
    { "stationOrder": 19, "stationName": "茶庵殿", "longitude": 120.831255, "latitude": 32.025179 },
    { "stationOrder": 20, "stationName": "人民路外环西路东", "longitude": 120.835792, "latitude": 32.022864 },
    { "stationOrder": 21, "stationName": "城港新村", "longitude": 120.841484, "latitude": 32.020671 },
    { "stationOrder": 22, "stationName": "市一中", "longitude": 120.846521, "latitude": 32.017935 },
    { "stationOrder": 23, "stationName": "端平桥", "longitude": 120.850367, "latitude": 32.017192 },
    { "stationOrder": 24, "stationName": "口腔医院北院", "longitude": 120.854216, "latitude": 32.016573 },
    { "stationOrder": 25, "stationName": "钟楼广场", "longitude": 120.857053, "latitude": 32.015928 },
    { "stationOrder": 26, "stationName": "友谊桥西", "longitude": 120.859122, "latitude": 32.015237 },
    { "stationOrder": 27, "stationName": "环西文化广场①", "longitude": 120.861244, "latitude": 32.014686 }
  ]
}
